prava/__init__.py
prava/client.py
prava-0.1.30.dist-info/METADATA
prava-0.1.30.dist-info/WHEEL
prava-0.1.30.dist-info/RECORD
