Metadata-Version: 2.4
Name: prava
Version: 0.1.30
Summary: Prava Python SDK for computer-use automation
Project-URL: Homepage, https://prava.co
Project-URL: Repository, https://github.com/pravaco/prava-sdk
Author: Prava AI
License: MIT
Keywords: api,automation,computer-use,prava,sdk
Requires-Python: <3.13,>=3.8
Requires-Dist: requests>=2.27.0
